odoo/addons/rest_log/README.rst
odoo/addons/rest_log/__init__.py
odoo/addons/rest_log/__manifest__.py
odoo/addons/rest_log/exceptions.py
odoo/addons/rest_log/hooks.py
odoo/addons/rest_log/components/__init__.py
odoo/addons/rest_log/components/service.py
odoo/addons/rest_log/data/ir_config_parameter_data.xml
odoo/addons/rest_log/data/ir_cron_data.xml
odoo/addons/rest_log/i18n/it.po
odoo/addons/rest_log/i18n/rest_log.pot
odoo/addons/rest_log/models/__init__.py
odoo/addons/rest_log/models/rest_log.py
odoo/addons/rest_log/readme/CONFIGURE.md
odoo/addons/rest_log/readme/CONTRIBUTORS.md
odoo/addons/rest_log/readme/CREDITS.md
odoo/addons/rest_log/readme/DESCRIPTION.md
odoo/addons/rest_log/readme/HISTORY.md
odoo/addons/rest_log/security/groups.xml
odoo/addons/rest_log/security/ir.model.access.csv
odoo/addons/rest_log/static/description/icon.png
odoo/addons/rest_log/static/description/index.html
odoo/addons/rest_log/tests/__init__.py
odoo/addons/rest_log/tests/common.py
odoo/addons/rest_log/tests/test_db_logging.py
odoo/addons/rest_log/views/menu.xml
odoo/addons/rest_log/views/rest_log_views.xml
odoo_addon_rest_log-18.0.1.0.1.dist-info/METADATA
odoo_addon_rest_log-18.0.1.0.1.dist-info/WHEEL
odoo_addon_rest_log-18.0.1.0.1.dist-info/top_level.txt
odoo_addon_rest_log-18.0.1.0.1.dist-info/RECORD
