Metadata-Version: 2.1
Name: odoo-addon-rest_log
Version: 18.0.1.0.1
Requires-Python: >=3.10
Requires-Dist: odoo-addon-base_rest==18.0.*
Requires-Dist: odoo==18.0.*
Summary: Track REST API calls into DB
Home-page: https://github.com/OCA/rest-framework
License: LGPL-3
Author: Camptocamp, ACSONE, Odoo Community Association (OCA)
Author-email: support@odoo-community.org
Classifier: Programming Language :: Python
Classifier: Framework :: Odoo
Classifier: Framework :: Odoo :: 18.0
Classifier: License :: OSI Approved :: GNU Lesser General Public License v3 (LGPLv3)
Classifier: Development Status :: 4 - Beta
